mizumi/core.py
mizumi/exceptions.py
mizumi-0.1.0.dist-info/METADATA
mizumi-0.1.0.dist-info/WHEEL
mizumi-0.1.0.dist-info/licenses/LICENSE
mizumi-0.1.0.dist-info/RECORD
