Metadata-Version: 2.4
Name: mizumi
Version: 0.1.0
Summary: Reliable structured outputs from unreliable LLMs.
Project-URL: Homepage, https://github.com/fechad/mizumi
Project-URL: Repository, https://github.com/fechad/mizumi
Author-email: Fedwin Chatelier <certendtechnologies@gmail.com>
License: 
License-File: LICENSE
Requires-Python: >=3.8
Requires-Dist: openai>=1.0
Requires-Dist: pydantic>=2.0
Requires-Dist: tenacity>=8.0
